coopapi/__init__.py
coopapi/apiShell.py
coopapi/enums.py
coopapi/errors.py
coopapi/http_request.py
coopapi/http_request_handlers.py
coopapi-1.1.dist-info/METADATA
coopapi-1.1.dist-info/WHEEL
coopapi-1.1.dist-info/top_level.txt
coopapi-1.1.dist-info/RECORD
