Metadata-Version: 2.1
Name: coopapi
Version: 1.1
Summary: Tools for setting up an API. Built on the FastAPI framework
Home-page: https://github.com/tylertjburns/coopapi
Author: tburns
Author-email: tyler.tj.burns@gmail.com
License: MIT
Platform: UNKNOWN
Classifier: Development Status :: 3 - Alpha
Classifier: License :: OSI Approved :: MIT License
Classifier: Programming Language :: Python
Classifier: Programming Language :: Python :: 3.5
Classifier: Programming Language :: Python :: 3.6
Classifier: Topic :: Software Development :: Libraries
Classifier: Topic :: Software Development :: Libraries :: Python Modules
Classifier: Intended Audience :: Developers
Requires-Python: >3.5
Requires-Dist: anyio (>=3.6.2)
Requires-Dist: certifi (>=2022.12.7)
Requires-Dist: charset-normalizer (>=3.0.1)
Requires-Dist: click (>=8.1.3)
Requires-Dist: colorama (>=0.4.6)
Requires-Dist: contourpy (>=1.1.0)
Requires-Dist: cooptools (>=1.9)
Requires-Dist: cycler (>=0.11.0)
Requires-Dist: fastapi (>=0.89.0)
Requires-Dist: fonttools (>=4.40.0)
Requires-Dist: h11 (>=0.14.0)
Requires-Dist: idna (>=3.4)
Requires-Dist: kiwisolver (>=1.4.4)
Requires-Dist: matplotlib (>=3.7.2)
Requires-Dist: numpy (>=1.25.0)
Requires-Dist: packaging (>=23.1)
Requires-Dist: pandas (>=2.0.3)
Requires-Dist: Pillow (>=10.0.0)
Requires-Dist: pydantic (>=1.10.4)
Requires-Dist: pyparsing (>=3.0.9)
Requires-Dist: python-dateutil (>=2.8.2)
Requires-Dist: pytz (>=2023.3)
Requires-Dist: requests (>=2.28.2)
Requires-Dist: scipy (>=1.11.1)
Requires-Dist: six (>=1.16.0)
Requires-Dist: sniffio (>=1.3.0)
Requires-Dist: starlette (>=0.22.0)
Requires-Dist: typing-extensions (>=4.4.0)
Requires-Dist: tzdata (>=2023.3)
Requires-Dist: urllib3 (>=1.26.14)
Requires-Dist: uvicorn (>=0.20.0)
